iap/__init__.py
iap/exceptions.py
iap/forms.py
iap/settings.py
iap/utils.py
iap/widgets.py
iap-2.3.3.dist-info/LICENSE
iap-2.3.3.dist-info/METADATA
iap-2.3.3.dist-info/WHEEL
iap-2.3.3.dist-info/top_level.txt
iap-2.3.3.dist-info/RECORD
