Metadata-Version: 2.1
Name: iap
Version: 2.3.3
Summary: Python utilities for working with Apple In-App Purchases (IAP)
Home-page: https://github.com/educreations/python-iap
Author: Educreations Engineering
Author-email: engineering@educreations.com
License: MIT
Keywords: iap appstore django
Platform: UNKNOWN
Classifier: Programming Language :: Python :: 2
Classifier: Programming Language :: Python :: 3
Classifier: License :: OSI Approved :: MIT License
Classifier: Operating System :: OS Independent
Provides-Extra: test
